setup.cfg
setup.py
scrapy_tools/__init__.py
scrapy_tools.egg-info/PKG-INFO
scrapy_tools.egg-info/SOURCES.txt
scrapy_tools.egg-info/dependency_links.txt
scrapy_tools.egg-info/top_level.txt
scrapy_tools/cluster/__init__.py
scrapy_tools/cluster/redis/__init__.py
scrapy_tools/cluster/redis/redis.py
scrapy_tools/download/__init__.py
scrapy_tools/extensions/RabbitMQScheduler.py
scrapy_tools/extensions/RabbitMQSpiderQueue.py
scrapy_tools/extensions/RedisRFPDupeFilter.py
scrapy_tools/extensions/__init__.py
scrapy_tools/storage/__init__.py
scrapy_tools/storage/activemq.py
scrapy_tools/storage/elasticsearch.py
scrapy_tools/storage/mongodb.py
scrapy_tools/storage/mysql.py
scrapy_tools/storage/postgresql.py
scrapy_tools/storage/rabbitmq.py