Metadata-Version: 1.0
Name: scrapy-tools
Version: 0.0.5
Summary: tools for scrapy_tools, consist of middlewares
Home-page: http://blog.livedrof.com
Author: jack.cong
Author-email: congshuanglong@126.com
License: LGPL
Platform: UNKNOWN
